{
  "id": 493287,
  "index_code": "NDX",
  "name": "纳指100",
  "ttype": "1",
  "pe": 35.4517,
  "pb": 9.7287,
  "pe_percentile": 0.8276,
  "pb_percentile": 0.9796,
  "roe": 0.2744,
  "yeild": 0.0051,
  "ts": 1757433600000,
  "eva_type": "high",
  "eva_type_int": 2,
  "url": "https://danjuanfunds.com/funding/160213?channel=1800100001&source=guzhi__web_20171001",
  "bond_yeild": 0.05,
  "begin_at": 1433347200000,
  "created_at": 1757500320350,
  "updated_at": 1757500320350,
  "peg": 1.7595,
  "pb_flag": false,
  "source": "5",
  "pb_over_history": 0.0204,
  "pe_over_history": 0.1724,
  "date": "09-10"
}