{
  "id": 481199,
  "index_code": "NDX",
  "name": "纳指100",
  "ttype": "1",
  "pe": 37.3931,
  "pb": 9.6963,
  "pe_percentile": 0.934,
  "pb_percentile": 0.9828,
  "roe": 0.2593,
  "yeild": 0.0056,
  "ts": 1735833600000,
  "eva_type": "high",
  "eva_type_int": 2,
  "url": "https://danjuanfunds.com/funding/160213?channel=1800100001&source=guzhi__web_20171001",
  "bond_yeild": 0.05,
  "begin_at": 1411488000000,
  "created_at": 1735897763212,
  "updated_at": 1735897763212,
  "peg": 1.8558,
  "pb_flag": false,
  "pb_over_history": 0.0172,
  "pe_over_history": 0.066,
  "date": "01-03"
}