{
  "id": 497768,
  "index_code": "NDX",
  "name": "纳指100",
  "ttype": "1",
  "pe": 36.6628,
  "pb": 10.251,
  "pe_percentile": 0.8868,
  "pb_percentile": 0.996,
  "roe": 0.2796,
  "yeild": 0.0047,
  "ts": 1765296000000,
  "eva_type": "high",
  "eva_type_int": 2,
  "url": "https://danjuanfunds.com/funding/160213?channel=1800100001&source=guzhi__web_20171001",
  "bond_yeild": 0.05,
  "begin_at": 1440604800000,
  "created_at": 1765362720310,
  "updated_at": 1765362720310,
  "peg": 1.8196,
  "pb_flag": false,
  "source": "5",
  "date": "12-10",
  "pb_over_history": 0.004,
  "pe_over_history": 0.1132
}