{
  "id": 484413,
  "index_code": "NDX",
  "name": "纳指100",
  "ttype": "1",
  "pe": 32.4005,
  "pb": 8.5015,
  "pe_percentile": 0.6724,
  "pb_percentile": 0.7928,
  "roe": 0.2624,
  "yeild": 0.0063,
  "ts": 1742745600000,
  "eva_type": "high",
  "eva_type_int": 2,
  "url": "https://danjuanfunds.com/funding/160213?channel=1800100001&source=guzhi__web_20171001",
  "bond_yeild": 0.05,
  "begin_at": 1418140800000,
  "created_at": 1742810966737,
  "updated_at": 1742810966737,
  "peg": 1.608,
  "pb_flag": false,
  "pb_over_history": 0.2072,
  "pe_over_history": 0.3276,
  "date": "03-24"
}