{
  "id": 488062,
  "index_code": "NDX",
  "name": "纳指100",
  "ttype": "1",
  "pe": 33.3402,
  "pb": 8.8854,
  "pe_percentile": 0.7004,
  "pb_percentile": 0.8576,
  "roe": 0.2665,
  "yeild": 0.0059,
  "ts": 1747670400000,
  "eva_type": "high",
  "eva_type_int": 2,
  "url": "https://danjuanfunds.com/funding/160213?channel=1800100001&source=guzhi__web_20171001",
  "bond_yeild": 0.05,
  "begin_at": 1422892800000,
  "created_at": 1747737000640,
  "updated_at": 1747737000640,
  "peg": 1.6547,
  "pb_flag": false,
  "source": "5",
  "date": "05-20",
  "pb_over_history": 0.1424,
  "pe_over_history": 0.2996
}